[
    {
        "train_config": {
            "ar": 100000,
            "bg": 0,
            "de": 10000,
            "el": 0,
            "en": 0,
            "es": 100000,
            "fr": 100000,
            "hi": 1000,
            "ru": 10000,
            "sw": 10000,
            "th": 100000,
            "tr": 0,
            "ur": 100000,
            "vi": 100000,
            "zh": 1000
        },
        "eval_results": {
            "en": "0.8296902",
            "fr": "0.86825264",
            "es": "0.85632896",
            "de": "0.8561111",
            "el": "0.8989582",
            "bg": "0.86649793",
            "ru": "0.8569864",
            "tr": "0.84518284",
            "ar": "0.8392958",
            "vi": "0.7950251",
            "th": "0.8138926",
            "zh": "0.82814336",
            "hi": "0.7545549",
            "sw": "0.83641076",
            "ur": "0.84212214"
        }
    },
    {
        "train_config": {
            "ar": 100000,
            "bg": 100000,
            "de": 100000,
            "el": 1000,
            "en": 0,
            "es": 0,
            "fr": 1000,
            "hi": 1000,
            "ru": 100000,
            "sw": 1000,
            "th": 10000,
            "tr": 1000,
            "ur": 1000,
            "vi": 100000,
            "zh": 0
        },
        "eval_results": {
            "en": "0.8390065",
            "fr": "0.8702573",
            "es": "0.8585315",
            "de": "0.8573668",
            "el": "0.8890795",
            "bg": "0.86540985",
            "ru": "0.85922205",
            "tr": "0.8437436",
            "ar": "0.843029",
            "vi": "0.8015792",
            "th": "0.8151108",
            "zh": "0.83056474",
            "hi": "0.7644546",
            "sw": "0.834598",
            "ur": "0.8421347"
        }
    },
    {
        "train_config": {
            "ar": 0,
            "bg": 0,
            "de": 100000,
            "el": 10000,
            "en": 10000,
            "es": 0,
            "fr": 1000,
            "hi": 10000,
            "ru": 0,
            "sw": 0,
            "th": 100000,
            "tr": 1000,
            "ur": 0,
            "vi": 0,
            "zh": 100000
        },
        "eval_results": {
            "en": "0.78060377",
            "fr": "0.86163217",
            "es": "0.83875763",
            "de": "0.85682243",
            "el": "0.8910058",
            "bg": "0.8600439",
            "ru": "0.84946704",
            "tr": "0.8215979",
            "ar": "0.8184284",
            "vi": "0.7588503",
            "th": "0.76470625",
            "zh": "0.7899352",
            "hi": "0.7484153",
            "sw": "0.79022175",
            "ur": "0.822819"
        }
    },
    {
        "train_config": {
            "ar": 1000,
            "bg": 0,
            "de": 0,
            "el": 1000,
            "en": 1000,
            "es": 0,
            "fr": 1000,
            "hi": 0,
            "ru": 1000,
            "sw": 1000,
            "th": 0,
            "tr": 0,
            "ur": 100000,
            "vi": 100000,
            "zh": 100000
        },
        "eval_results": {
            "en": "0.8525371",
            "fr": "0.85058737",
            "es": "0.8356279",
            "de": "0.8479773",
            "el": "0.8483114",
            "bg": "0.83708483",
            "ru": "0.8426632",
            "tr": "0.8436233",
            "ar": "0.8363878",
            "vi": "0.8014957",
            "th": "0.8118774",
            "zh": "0.8062373",
            "hi": "0.76132053",
            "sw": "0.8299939",
            "ur": "0.8328652"
        }
    },
    {
        "train_config": {
            "ar": 100000,
            "bg": 0,
            "de": 0,
            "el": 100000,
            "en": 100000,
            "es": 100000,
            "fr": 0,
            "hi": 1000,
            "ru": 10000,
            "sw": 100000,
            "th": 0,
            "tr": 0,
            "ur": 1000,
            "vi": 0,
            "zh": 100000
        },
        "eval_results": {
            "en": "0.8341146",
            "fr": "0.87527204",
            "es": "0.8598568",
            "de": "0.85694385",
            "el": "0.89315295",
            "bg": "0.8629378",
            "ru": "0.85923547",
            "tr": "0.84513384",
            "ar": "0.8390477",
            "vi": "0.7997856",
            "th": "0.8117663",
            "zh": "0.82720256",
            "hi": "0.7662951",
            "sw": "0.8382501",
            "ur": "0.8424495"
        }
    },
    {
        "train_config": {
            "ar": 1000,
            "bg": 0,
            "de": 1000,
            "el": 100000,
            "en": 0,
            "es": 1000,
            "fr": 100000,
            "hi": 100000,
            "ru": 100000,
            "sw": 100000,
            "th": 100000,
            "tr": 0,
            "ur": 100000,
            "vi": 100000,
            "zh": 10000
        },
        "eval_results": {
            "en": "0.83709323",
            "fr": "0.8547243",
            "es": "0.8608903",
            "de": "0.8607448",
            "el": "0.89350355",
            "bg": "0.86770386",
            "ru": "0.86012685",
            "tr": "0.84951895",
            "ar": "0.83994925",
            "vi": "0.7889585",
            "th": "0.8163769",
            "zh": "0.8332527",
            "hi": "0.76268846",
            "sw": "0.8333213",
            "ur": "0.8414267"
        }
    },
    {
        "train_config": {
            "ar": 10000,
            "bg": 10000,
            "de": 0,
            "el": 100000,
            "en": 1000,
            "es": 0,
            "fr": 100000,
            "hi": 100000,
            "ru": 100000,
            "sw": 1000,
            "th": 0,
            "tr": 10000,
            "ur": 1000,
            "vi": 10000,
            "zh": 0
        },
        "eval_results": {
            "en": "0.8478744",
            "fr": "0.86271596",
            "es": "0.86046773",
            "de": "0.8582272",
            "el": "0.89207673",
            "bg": "0.86405027",
            "ru": "0.86250234",
            "tr": "0.84445715",
            "ar": "0.83769006",
            "vi": "0.80072975",
            "th": "0.82072216",
            "zh": "0.8429919",
            "hi": "0.768696",
            "sw": "0.84290385",
            "ur": "0.84334314"
        }
    },
    {
        "train_config": {
            "ar": 100000,
            "bg": 0,
            "de": 1000,
            "el": 100000,
            "en": 1000,
            "es": 100000,
            "fr": 100000,
            "hi": 100000,
            "ru": 100000,
            "sw": 100000,
            "th": 100000,
            "tr": 0,
            "ur": 0,
            "vi": 0,
            "zh": 100000
        },
        "eval_results": {
            "en": "0.8354487",
            "fr": "0.8637379",
            "es": "0.8554432",
            "de": "0.8611253",
            "el": "0.89901054",
            "bg": "0.86764103",
            "ru": "0.8570944",
            "tr": "0.84239054",
            "ar": "0.8377005",
            "vi": "0.7945899",
            "th": "0.8153732",
            "zh": "0.83339614",
            "hi": "0.7614693",
            "sw": "0.8327023",
            "ur": "0.8412234"
        }
    },
    {
        "train_config": {
            "ar": 0,
            "bg": 100000,
            "de": 0,
            "el": 100000,
            "en": 100000,
            "es": 100000,
            "fr": 0,
            "hi": 100000,
            "ru": 100000,
            "sw": 10000,
            "th": 0,
            "tr": 0,
            "ur": 10000,
            "vi": 0,
            "zh": 1000
        },
        "eval_results": {
            "en": "0.80953044",
            "fr": "0.85350645",
            "es": "0.85806125",
            "de": "0.8618865",
            "el": "0.89208794",
            "bg": "0.8662412",
            "ru": "0.8593552",
            "tr": "0.84485835",
            "ar": "0.83966047",
            "vi": "0.7907945",
            "th": "0.7932556",
            "zh": "0.804757",
            "hi": "0.75959593",
            "sw": "0.81476104",
            "ur": "0.8278622"
        }
    },
    {
        "train_config": {
            "ar": 100000,
            "bg": 0,
            "de": 0,
            "el": 1000,
            "en": 0,
            "es": 100000,
            "fr": 100000,
            "hi": 10000,
            "ru": 0,
            "sw": 0,
            "th": 0,
            "tr": 0,
            "ur": 100000,
            "vi": 100000,
            "zh": 0
        },
        "eval_results": {
            "en": "0.8321285",
            "fr": "0.86541563",
            "es": "0.82031006",
            "de": "0.8422745",
            "el": "0.8717559",
            "bg": "0.83675146",
            "ru": "0.8488791",
            "tr": "0.83031696",
            "ar": "0.8260362",
            "vi": "0.7823711",
            "th": "0.7845743",
            "zh": "0.7895037",
            "hi": "0.775328",
            "sw": "0.8121867",
            "ur": "0.8234709"
        }
    }
]